xblobs/__init__.py
xblobs/blob.py
xblobs/detect.py
xblobs-1.0.2.dist-info/LICENSE
xblobs-1.0.2.dist-info/WHEEL
xblobs-1.0.2.dist-info/METADATA
xblobs-1.0.2.dist-info/RECORD
